provechain/__init__.py
provechain/cli.py
provechain/ledger.py
provechain-0.1.1.dist-info/licenses/LICENSE
provechain-0.1.1.dist-info/METADATA
provechain-0.1.1.dist-info/WHEEL
provechain-0.1.1.dist-info/entry_points.txt
provechain-0.1.1.dist-info/top_level.txt
provechain-0.1.1.dist-info/RECORD
