Metadata-Version: 2.4
Name: provechain
Version: 0.1.1
Summary: Blockchain Timestamping for Source Code - Prove code authorship with cryptographic proofs
Home-page: https://github.com/Aramantos/provechain
Author: John Doyle
Author-email: john.doyle.mail@icloud.com
Project-URL: Bug Reports, https://github.com/Aramantos/provechain/issues
Project-URL: Source, https://github.com/Aramantos/provechain
Keywords: blockchain timestamp proof authorship ip-protection git source-code
Classifier: Development Status :: 3 - Alpha
Classifier: Intended Audience :: Developers
Classifier: Topic :: Software Development :: Version Control
Classifier: Topic :: Security :: Cryptography
Classifier: License :: OSI Approved :: MIT License
Classifier: Programming Language :: Python :: 3
Classifier: Programming Language :: Python :: 3.8
Classifier: Programming Language :: Python :: 3.9
Classifier: Programming Language :: Python :: 3.10
Classifier: Programming Language :: Python :: 3.11
Requires-Python: >=3.8
License-File: LICENSE
Requires-Dist: PyYAML>=6.0.1
Requires-Dist: cryptography>=41.0.4
Requires-Dist: rich>=13.7.0
Dynamic: author
Dynamic: author-email
Dynamic: classifier
Dynamic: description
Dynamic: description-content-type
Dynamic: home-page
Dynamic: keywords
Dynamic: license-file
Dynamic: project-url
Dynamic: requires-dist
Dynamic: requires-python
Dynamic: summary
